phcli/__init__.py
phcli/__main__.py
phcli/define_value.py
phcli/ph_admin/__init__.py
phcli/ph_admin/__main__.py
phcli/ph_admin/ph_partner.py
phcli/ph_admin/ph_role.py
phcli/ph_admin/ph_scope.py
phcli/ph_admin/ph_user.py
phcli/ph_admin/ph_models/__init__.py
phcli/ph_auto_setup/__init__.py
phcli/ph_auto_setup/__main__.py
phcli/ph_auto_setup/ec2_operation/__init__.py
phcli/ph_auto_setup/ec2_operation/__main__.py
phcli/ph_auto_setup/ec2_operation/ph_c9_operation.py
phcli/ph_auto_setup/ec2_operation/ph_ec2_operation.py
phcli/ph_auto_setup/ec2_operation/ph_jupyter_operation.py
phcli/ph_auto_setup/emr_operation/__init__.py
phcli/ph_auto_setup/emr_operation/__main__.py
phcli/ph_auto_setup/emr_operation/ph_emr_operation.py
phcli/ph_aws/PhDynamoDB.py
phcli/ph_aws/__init__.py
phcli/ph_aws/aws_root.py
phcli/ph_aws/ph_cloud_watch.py
phcli/ph_aws/ph_s3.py
phcli/ph_aws/ph_sts.py
phcli/ph_dag/__init__.py
phcli/ph_dag/__main__.py
phcli/ph_dag/ph_airflow/__init__.py
phcli/ph_dag/ph_airflow/__main__.py
phcli/ph_dag/ph_airflow/model/__init__.py
phcli/ph_data_clean/__init__.py
phcli/ph_data_clean/__main__.py
phcli/ph_data_clean/clean/__init__.py
phcli/ph_data_clean/clean/chc_data_clean.py
phcli/ph_data_clean/clean/cleaner_factory.py
phcli/ph_data_clean/clean/common_func.py
phcli/ph_data_clean/clean/cpa_gyc_data_clean.py
phcli/ph_data_clean/clean/data_clean.py
phcli/ph_data_clean/clean/product_data_clean.py
phcli/ph_data_clean/clean/universe_data_clean.py
phcli/ph_data_clean/mapping/__init__.py
phcli/ph_data_clean/mapping/chc_acn.py
phcli/ph_data_clean/mapping/chc_az.py
phcli/ph_data_clean/mapping/chc_ca.py
phcli/ph_data_clean/mapping/chc_pfizer.py
phcli/ph_data_clean/mapping/chc_sanofi.py
phcli/ph_data_clean/mapping/chc_servier.py
phcli/ph_data_clean/mapping/cpa_amgen.py
phcli/ph_data_clean/mapping/cpa_aohong.py
phcli/ph_data_clean/mapping/cpa_astellas.py
phcli/ph_data_clean/mapping/cpa_bayer.py
phcli/ph_data_clean/mapping/cpa_beite.py
phcli/ph_data_clean/mapping/cpa_bms.py
phcli-4.0.0.dist-info/LICENSE
phcli-4.0.0.dist-info/METADATA
phcli-4.0.0.dist-info/WHEEL
phcli-4.0.0.dist-info/entry_points.txt
phcli-4.0.0.dist-info/top_level.txt
phcli-4.0.0.dist-info/RECORD
