Metadata-Version: 2.1
Name: phcli
Version: 4.0.0
Summary: pharbers dag scheduler config
Home-page: UNKNOWN
Author: Alfred Yang
Author-email: alfredyang@pharbers.com
Maintainer: ClockQ,AlexQian,hbzhao
Maintainer-email: zyqi@pharbers.com,pqian@pharbers.com,15847059648@163.com
License: UNKNOWN
Platform: UNKNOWN
Classifier: License :: OSI Approved :: MIT License
Classifier: Operating System :: OS Independent
Requires-Python: >=2.7
Requires-Dist: boto3
Requires-Dist: click
Requires-Dist: pandas
Requires-Dist: psycopg2
Requires-Dist: pymysql
Requires-Dist: pypinyin
Requires-Dist: pyyaml
Requires-Dist: requests
Requires-Dist: sqlalchemy
Requires-Dist: xlrd
